{
  "session_id": "4bc56f72-b77f-4657-a1d5-6d22ae4c0e3c",
  "project_path": "/home/rookslog/workspace/projects/get-shit-done-reflect",
  "start_time": "2026-03-19T06:55:25.372Z",
  "duration_minutes": 741,
  "user_message_count": 18,
  "assistant_message_count": 117,
  "tool_counts": {
    "Bash": 26,
    "Read": 20,
    "Grep": 9,
    "Agent": 1,
    "Write": 2,
    "ToolSearch": 1,
    "WebSearch": 2,
    "WebFetch": 3,
    "Skill": 1
  },
  "languages": {
    "Markdown": 19,
    "JavaScript": 3
  },
  "git_commits": 1,
  "git_pushes": 0,
  "input_tokens": 194,
  "output_tokens": 30033,
  "first_prompt": "/gsdr:resume-work .planning/.continue-here.md",
  "user_interruptions": 2,
  "user_response_times": [
    427.014,
    427.014,
    8.51,
    188.54,
    191.654,
    267.688,
    918.81,
    368.326,
    309.748,
    2.034,
    80.438
  ],
  "tool_errors": 2,
  "tool_error_categories": {
    "Command Failed": 1,
    "Other": 1
  },
  "uses_task_agent": true,
  "uses_mcp": false,
  "uses_web_search": true,
  "uses_web_fetch": true,
  "lines_added": 297,
  "lines_removed": 0,
  "files_modified": 1,
  "message_hours": [
    2,
    2,
    2,
    2,
    2,
    3,
    3,
    3,
    3,
    3,
    3,
    3,
    3,
    3,
    3,
    3,
    3,
    15
  ],
  "user_message_timestamps": [
    "2026-03-19T06:55:25.372Z",
    "2026-03-19T06:55:24.938Z",
    "2026-03-19T06:55:32.786Z",
    "2026-03-19T06:55:32.786Z",
    "2026-03-19T06:56:14.060Z",
    "2026-03-19T07:03:41.127Z",
    "2026-03-19T07:03:41.127Z",
    "2026-03-19T07:05:37.819Z",
    "2026-03-19T07:09:55.621Z",
    "2026-03-19T07:09:58.735Z",
    "2026-03-19T07:11:14.769Z",
    "2026-03-19T07:30:34.721Z",
    "2026-03-19T07:38:18.341Z",
    "2026-03-19T07:45:08.787Z",
    "2026-03-19T07:47:37.595Z",
    "2026-03-19T07:47:49.709Z",
    "2026-03-19T07:49:08.113Z",
    "2026-03-19T19:15:59.317Z"
  ]
}